utilsMini/__init__.py
utilsMini/entity.py
utilsMini/parse.py
utilsMini/sharpDateTime.py
utilsMini/uitiy.py
utils_mini-0.1.6.dist-info/METADATA
utils_mini-0.1.6.dist-info/WHEEL
utils_mini-0.1.6.dist-info/top_level.txt
utils_mini-0.1.6.dist-info/RECORD
