Metadata-Version: 2.1
Name: utils-mini
Version: 0.1.6
Summary: ('python的一些简单的工具方法', 'Some simple tools and methods of Python')
Home-page: https://github.com/beincy/utils-mini
Author: beincy
Author-email: bianhui0524@sina.com
Maintainer: 卞辉(beincy)
Maintainer-email: bianhui0524@sina.com
License: MIT
Platform: all
Classifier: Development Status :: 4 - Beta
Classifier: License :: OSI Approved :: MIT License
Classifier: Programming Language :: Python :: 3.5
Classifier: Programming Language :: Python :: 3.6
Classifier: Programming Language :: Python :: 3.7
Requires-Dist: ujson
